warm/__init__.py
warm/engine.py
warm/functional.py
warm/module.py
warm/util.py
pywarm-0.4.1.dist-info/LICENSE.md
pywarm-0.4.1.dist-info/WHEEL
pywarm-0.4.1.dist-info/METADATA
pywarm-0.4.1.dist-info/RECORD
