Metadata-Version: 2.1
Name: pywarm
Version: 0.4.1
Summary: A cleaner way to build neural networks for PyTorch.
Home-page: https://github.com/blue-season/pywarm
License: MIT
Keywords: pywarm,pytorch,neural network,deep learning
Author: blue-season
Author-email: very.blue.season@gmail.com
Requires-Python: >=3.6
Classifier: License :: OSI Approved :: MIT License
Classifier: Programming Language :: Python :: 3
Classifier: Programming Language :: Python :: 3.6
Classifier: Programming Language :: Python :: 3.7
Project-URL: Repository, https://github.com/blue-season/pywarm
